mirrorshades/__init__.py
mirrorshades/__main__.py
mirrorshades/config.py
mirrorshades/agents/__init__.py
mirrorshades/agents/base.py
mirrorshades/agents/command.py
mirrorshades/agents/git.py
mirrorshades/agents/github.py
mirrorshades/agents/gitlab.py
mirrorshades/agents/rclone.py
mirrorshades-0.2.0.dist-info/Apache-2.0.txt
mirrorshades-0.2.0.dist-info/CC-BY-4.0.txt
mirrorshades-0.2.0.dist-info/CC0-1.0.txt
mirrorshades-0.2.0.dist-info/METADATA
mirrorshades-0.2.0.dist-info/WHEEL
mirrorshades-0.2.0.dist-info/entry_points.txt
mirrorshades-0.2.0.dist-info/top_level.txt
mirrorshades-0.2.0.dist-info/RECORD
